webdriverdownloader/__init__.py
webdriverdownloader/cli.py
webdriverdownloader/util.py
webdriverdownloader/webdriverdownloader.py
webdriverdownloader-1.1.0.4.dist-info/LICENSE
webdriverdownloader-1.1.0.4.dist-info/METADATA
webdriverdownloader-1.1.0.4.dist-info/WHEEL
webdriverdownloader-1.1.0.4.dist-info/entry_points.txt
webdriverdownloader-1.1.0.4.dist-info/top_level.txt
webdriverdownloader-1.1.0.4.dist-info/RECORD
